pykantorovich/__init__.py
pykantorovich/kantorovich.py
pykantorovich-0.2.0.dist-info/LICENSE
pykantorovich-0.2.0.dist-info/WHEEL
pykantorovich-0.2.0.dist-info/METADATA
pykantorovich-0.2.0.dist-info/RECORD
